movdata/__init__.py
movdata/_etd.cpython-38-darwin.so
movdata/astronomy.py
movdata/base.py
movdata/cluster.py
movdata/datanalyzer.py
movdata/dataschedule.py
movdata/eetools.py
movdata/etd_range.py
movdata/geofence.py
movdata/kde_range.py
movdata/lineclip.py
movdata/movingwindow.py
movdata/percentile_area.py
movdata/proximity.py
movdata/raster.py
movdata/seasons.py
movdata/utils.py
movdata/version.py
movdata-0.1.20rc12.dist-info/LICENSE
movdata-0.1.20rc12.dist-info/METADATA
movdata-0.1.20rc12.dist-info/WHEEL
movdata-0.1.20rc12.dist-info/top_level.txt
movdata-0.1.20rc12.dist-info/RECORD
