Metadata-Version: 2.1
Name: movdata
Version: 0.1.20rc12
Summary: Movement Ecology Tools For Python
Home-page: https://github.com/wildlife-dynamics/movdata
Author: Jake Wall
Author-email: movementecologytools@gmail.com
License: BSD 3-Clause
Platform: Posix; MacOS X; Windows
Classifier: License :: OSI Approved :: BSD License
Classifier: Intended Audience :: Science/Research
Classifier: Intended Audience :: Developers
Classifier: Topic :: Scientific/Engineering
Classifier: Programming Language :: Python
Classifier: Programming Language :: Python :: 3
Classifier: Programming Language :: Python :: 3.4
Classifier: Programming Language :: Python :: 3.5
Classifier: Programming Language :: Python :: 3.6
Classifier: Programming Language :: Python :: 3.7
License-File: LICENSE
Requires-Dist: geopandas
Requires-Dist: gdal
Requires-Dist: fiona
Requires-Dist: geographiclib
Requires-Dist: numpy
Requires-Dist: scipy
Requires-Dist: scikit-learn
Requires-Dist: geojson
Requires-Dist: descartes
Requires-Dist: python-dateutil
Requires-Dist: rasterio
Requires-Dist: rasterstats
Requires-Dist: joblib
Requires-Dist: pyOpenSSL
Requires-Dist: google-api-python-client
Requires-Dist: earthengine-api
Requires-Dist: oauth2client
Requires-Dist: astropy
Requires-Dist: cython
